{
 "__fileName__": "data/frFR_Text/meta/StringList/Conv_Frac_GV2_StudyReturn.stl",
 "__snoID__": 1038977,
 "__type__": "StringListDefinition",
 "__typeHash__": 3672216444,
 "arStrings": [
  {
   "__type__": "StringTableEntry",
   "__typeHash__": 3844612145,
   "szLabel": "Line1.6DE47",
   "szText": "J’espère que vous avez eu plus de chance que moi.",
   "hLabel": 1512058033
  },
  {
   "__type__": "StringTableEntry",
   "__typeHash__": 3844612145,
   "szLabel": "Line1.6DE47.F",
   "szText": "J’espère que vous avez eu plus de chance que moi.",
   "hLabel": 1658725189
  }
 ],
 "ptMapStringTable": "0"
}
