{
 "__fileName__": "zhTW_Text/meta/StringList/Conv_QST_Scos_Epi_Cine_EPL.stl",
 "__snoID__": 973814,
 "__type__": "StringListDefinition",
 "__typeHash__": 3672216444,
 "arStrings": [
  {
   "__type__": "StringTableEntry",
   "__typeHash__": 3844612145,
   "szLabel": "MenuLabel",
   "szText": "赫拉迪姆的傳承",
   "hLabel": 4215274549
  },
  {
   "__type__": "StringTableEntry",
   "__typeHash__": 3844612145,
   "szLabel": "Line1.6DE47",
   "szText": "我花了很多時間才學會這套暗語。羅拉斯，希望你還記得怎麼解讀。你現在是最後的赫拉迪姆了。",
   "hLabel": 1512058033
  },
  {
   "__type__": "StringTableEntry",
   "__typeHash__": 3844612145,
   "szLabel": "Line7.6DE47",
   "szText": "我母親應該會希望我留在你身邊。她相信赫拉迪姆能解決一切問題。",
   "hLabel": 670931255
  },
  {
   "__type__": "StringTableEntry",
   "__typeHash__": 3844612145,
   "szLabel": "Line11.6DE47",
   "szText": "我現在的樣子，她說不定都不認得了。",
   "hLabel": 1865093314
  },
  {
   "__type__": "StringTableEntry",
   "__typeHash__": 3844612145,
   "szLabel": "Line13.6DE47",
   "szText": "現在想到她我還是很難過，但我也會想起你和多南。你們才不是什麼『全知的赫拉迪姆』。",
   "hLabel": 153061956
  },
  {
   "__type__": "StringTableEntry",
   "__typeHash__": 3844612145,
   "szLabel": "Line47.6DE47",
   "szText": "你們會痛苦不安、也會猶豫不決。",
   "hLabel": 30276587
  },
  {
   "__type__": "StringTableEntry",
   "__typeHash__": 3844612145,
   "szLabel": "Line15.6DE47",
   "szText": "但你們的友情很真誠。",
   "hLabel": 2735997894
  },
  {
   "__type__": "StringTableEntry",
   "__typeHash__": 3844612145,
   "szLabel": "Line17.6DE47",
   "szText": "在這漫漫長路上，那份友情支撐著我繼續向前。",
   "hLabel": 1023966536
  },
  {
   "__type__": "StringTableEntry",
   "__typeHash__": 3844612145,
   "szLabel": "Line19.6DE47",
   "szText": "你們的不完美之處給了我希望，來面對接下來的旅程。",
   "hLabel": 3606902474
  },
  {
   "__type__": "StringTableEntry",
   "__typeHash__": 3844612145,
   "szLabel": "Line21.6DE47",
   "szText": "來面對他…還有他的兄弟。",
   "hLabel": 1533863331
  },
  {
   "__type__": "StringTableEntry",
   "__typeHash__": 3844612145,
   "szLabel": "Line27.6DE47",
   "szText": "我不知道還有多少時間，但一定有更好的辦法。我必須找出來。靠我自己。",
   "hLabel": 692736553
  },
  {
   "__type__": "StringTableEntry",
   "__typeHash__": 3844612145,
   "szLabel": "Line31.6DE47",
   "szText": "我知道你會想跟我一起來。",
   "hLabel": 1202633348
  },
  {
   "__type__": "StringTableEntry",
   "__typeHash__": 3844612145,
   "szLabel": "Line33.6DE47",
   "szText": "但已經有人因為我不夠小心而喪命。我不能讓你冒險。",
   "hLabel": 3785569286
  },
  {
   "__type__": "StringTableEntry",
   "__typeHash__": 3844612145,
   "szLabel": "Line35.6DE47",
   "szText": "萬一我的判斷錯了，這個世界需要你活下來。收拾我的錯誤造成的後果。",
   "hLabel": 2073537928
  },
  {
   "__type__": "StringTableEntry",
   "__typeHash__": 3844612145,
   "szLabel": "Line37.6DE47",
   "szText": "我知道你不想聽這些，但你不可以放棄。這次不行。",
   "hLabel": 361506570
  },
  {
   "__type__": "StringTableEntry",
   "__typeHash__": 3844612145,
   "szLabel": "Line43.6DE47",
   "szText": "羅拉斯，祝我順利吧。如果一切照我的計劃發展…",
   "hLabel": 3454339303
  },
  {
   "__type__": "StringTableEntry",
   "__typeHash__": 3844612145,
   "szLabel": "Line45.6DE47",
   "szText": "我們永遠不會再見了。",
   "hLabel": 1742307945
  },
  {
   "__type__": "StringTableEntry",
   "__typeHash__": 3844612145,
   "szLabel": "Line1.6DE47.F",
   "szText": "我花了很多時間才學會這套暗語。羅拉斯，希望你還記得怎麼解讀。你現在是最後的赫拉迪姆了。",
   "hLabel": 1658725189
  },
  {
   "__type__": "StringTableEntry",
   "__typeHash__": 3844612145,
   "szLabel": "Line11.6DE47.F",
   "szText": "我現在的樣子，她說不定都不認得了。",
   "hLabel": 3862056854
  },
  {
   "__type__": "StringTableEntry",
   "__typeHash__": 3844612145,
   "szLabel": "Line13.6DE47.F",
   "szText": "現在想到她我還是很難過，但我也會想起你和多南。你們才不是什麼『全知的赫拉迪姆』。",
   "hLabel": 3475714456
  },
  {
   "__type__": "StringTableEntry",
   "__typeHash__": 3844612145,
   "szLabel": "Line15.6DE47.F",
   "szText": "但你們的友情很真誠。",
   "hLabel": 3089372058
  },
  {
   "__type__": "StringTableEntry",
   "__typeHash__": 3844612145,
   "szLabel": "Line17.6DE47.F",
   "szText": "在這漫漫長路上，那份友情支撐著我繼續向前。",
   "hLabel": 2703029660
  },
  {
   "__type__": "StringTableEntry",
   "__typeHash__": 3844612145,
   "szLabel": "Line19.6DE47.F",
   "szText": "你們的不完美之處給了我希望，來面對接下來的旅程。",
   "hLabel": 2316687262
  },
  {
   "__type__": "StringTableEntry",
   "__typeHash__": 3844612145,
   "szLabel": "Line21.6DE47.F",
   "szText": "來面對他…還有他的兄弟。",
   "hLabel": 3929858231
  },
  {
   "__type__": "StringTableEntry",
   "__typeHash__": 3844612145,
   "szLabel": "Line27.6DE47.F",
   "szText": "我不知道還有多少時間，但一定有更好的辦法。我必須找出來。靠我自己。",
   "hLabel": 2770831037
  },
  {
   "__type__": "StringTableEntry",
   "__typeHash__": 3844612145,
   "szLabel": "Line31.6DE47.F",
   "szText": "我知道你會想跟我一起來。",
   "hLabel": 3997659608
  },
  {
   "__type__": "StringTableEntry",
   "__typeHash__": 3844612145,
   "szLabel": "Line33.6DE47.F",
   "szText": "但已經有人因為我不夠小心而喪命。我不能讓你冒險。",
   "hLabel": 3611317210
  },
  {
   "__type__": "StringTableEntry",
   "__typeHash__": 3844612145,
   "szLabel": "Line35.6DE47.F",
   "szText": "萬一我的判斷錯了，這個世界需要你活下來。收拾我的錯誤造成的後果。",
   "hLabel": 3224974812
  },
  {
   "__type__": "StringTableEntry",
   "__typeHash__": 3844612145,
   "szLabel": "Line37.6DE47.F",
   "szText": "我知道你不想聽這些，但你不可以放棄。這次不行。",
   "hLabel": 2838632414
  },
  {
   "__type__": "StringTableEntry",
   "__typeHash__": 3844612145,
   "szLabel": "Line43.6DE47.F",
   "szText": "羅拉斯，祝我順利吧。如果一切照我的計劃發展…",
   "hLabel": 3679118587
  },
  {
   "__type__": "StringTableEntry",
   "__typeHash__": 3844612145,
   "szLabel": "Line45.6DE47.F",
   "szText": "我們永遠不會再見了。",
   "hLabel": 3292776189
  },
  {
   "__type__": "StringTableEntry",
   "__typeHash__": 3844612145,
   "szLabel": "Line47.6DE47.F",
   "szText": "你們會痛苦不安、也會猶豫不決。",
   "hLabel": 2906433791
  },
  {
   "__type__": "StringTableEntry",
   "__typeHash__": 3844612145,
   "szLabel": "Line7.6DE47.F",
   "szText": "我母親應該會希望我留在你身邊。她相信赫拉迪姆能解決一切問題。",
   "hLabel": 499697995
  }
 ],
 "ptMapStringTable": "0"
}
