{
 "__fileName__": "zhTW_Text/meta/StringList/Power_Druid_LightningStorm.stl",
 "__snoID__": 1115937,
 "__type__": "StringListDefinition",
 "__typeHash__": 3672216444,
 "arStrings": [
  {
   "__type__": "StringTableEntry",
   "__typeHash__": 3844612145,
   "szLabel": "name",
   "szText": "閃電風暴",
   "hLabel": 4062401
  },
  {
   "__type__": "StringTableEntry",
   "__typeHash__": 3844612145,
   "szLabel": "desc",
   "szText": "{c_label}每次雷擊靈力消耗：{/c}{c_resource}{Resource Cost}{/c}\r\n{if:ADVANCED_TOOLTIP}{c_label}幸運觸發機率：{/c}{c_resource}[{Combat Effect Chance}|%|]{/c}\r\n{/if}呼喚不斷成長的閃電風暴，每次雷擊造成 {c_number}{payload:DAMAGE}{/c} 點傷害。風暴引導的時間越長，雷擊的次數就越多，一次引導最多可提高至 {c_number}[{SF_16}+1]{/c} 次。",
   "hLabel": 3707583
  },
  {
   "__type__": "StringTableEntry",
   "__typeHash__": 3844612145,
   "szLabel": "rankup_desc",
   "szText": "\r\n{icon:bullet,1.2} 傷害 {icon:arrow,1.2} {c_number}{payload:DAMAGE}{/c}",
   "hLabel": 4074074671
  },
  {
   "__type__": "StringTableEntry",
   "__typeHash__": 3844612145,
   "szLabel": "Mod2_Description",
   "szText": "{c_important}閃電風暴{/c}的大小會保留至引導後 {c_number}{SF_10}{/c} 秒。",
   "hLabel": 1960229941
  },
  {
   "__type__": "StringTableEntry",
   "__typeHash__": 3844612145,
   "szLabel": "Mod2_Name",
   "szText": "強化閃電風暴",
   "hLabel": 2531142258
  },
  {
   "__type__": "StringTableEntry",
   "__typeHash__": 3844612145,
   "szLabel": "Mod0_Description",
   "szText": "{c_important}閃電風暴{/c}獲得額外 {c_number}1{/c} 次閃電強擊。",
   "hLabel": 3591940403
  },
  {
   "__type__": "StringTableEntry",
   "__typeHash__": 3844612145,
   "szLabel": "Mod0_Name",
   "szText": "盛怒閃電風暴",
   "hLabel": 2452871472
  },
  {
   "__type__": "StringTableEntry",
   "__typeHash__": 3844612145,
   "szLabel": "Mod1_Description",
   "szText": "{c_important}閃電風暴{/c}有 {c_number}[{SF_8}*100|%|]{/c} 機率使擊中的敵人定身，持續 {c_number}{buffduration:IMMOBILIZE}{/c} 秒。",
   "hLabel": 628601524
  },
  {
   "__type__": "StringTableEntry",
   "__typeHash__": 3844612145,
   "szLabel": "Mod1_Name",
   "szText": "原始閃電風暴",
   "hLabel": 2492006865
  }
 ],
 "ptMapStringTable": "0"
}
