{
 "__fileName__": "data/esES_Text/meta/StringList/Power_Paragon_Necro_Legendary_017.stl",
 "__snoID__": 1115769,
 "__type__": "StringListDefinition",
 "__typeHash__": 3672216444,
 "arStrings": [
  {
   "__type__": "StringTableEntry",
   "__typeHash__": 3844612145,
   "szLabel": "desc",
   "szText": "Golpear a enemigos con habilidades de {c_important}hueso{/c} aumenta tu daño un {c_number}[{SF_0}*100|%x|]{/c} y tu esencia máxima en {c_number}{SF_1}{/c} durante {c_number}{SF_3}{/c} s. Se acumula hasta un máximo de un {c_number}[{SF_0}*{SF_2}*100|%x|]{/c} más de daño y {c_number}[{SF_1}*{SF_2}]{/c} de esencia máxima.",
   "hLabel": 3707583
  },
  {
   "__type__": "StringTableEntry",
   "__typeHash__": 3844612145,
   "szLabel": "Buff1_Name",
   "szText": "Injerto óseo",
   "hLabel": 270276116
  },
  {
   "__type__": "StringTableEntry",
   "__typeHash__": 3844612145,
   "szLabel": "Buff1_Description",
   "szText": "Aumento de daño y esencia máxima al golpear a enemigos con habilidades de {c_important}hueso{/c}.",
   "hLabel": 2005335447
  }
 ],
 "ptMapStringTable": "0"
}
