{
 "__fileName__": "trTR_Text/meta/1473782",
 "__snoID__": 1473782,
 "__type__": "StringListDefinition",
 "__typeHash__": 3672216444,
 "arStrings": [
  {
   "__type__": "StringTableEntry",
   "__typeHash__": 3844612145,
   "szLabel": "Name",
   "szText": "Toz İçinde Bir Tanık",
   "hLabel": 4062401
  },
  {
   "__type__": "StringTableEntry",
   "__typeHash__": 3844612145,
   "szLabel": "Toast",
   "szText": "Pis Kokulu Mozole'den Kirli Vampir Kafatası'nı geri al. ",
   "hLabel": 141665387
  },
  {
   "__type__": "StringTableEntry",
   "__typeHash__": 3844612145,
   "szLabel": "Phase0Description",
   "szText": "Erys, Lort Zir ile ilgili daha çok şey öğrenebileceğimiz bir ayin biliyor. Önce Pis Kokulu Mozole'deki Kadim Vampirin kalıntılarını bulmalıyız.",
   "hLabel": 3577478917
  },
  {
   "__type__": "StringTableEntry",
   "__typeHash__": 3844612145,
   "szLabel": "Callback2Header",
   "szText": "Erys ile Pis Kokulu Mozole'ye gir",
   "hLabel": 514698856
  },
  {
   "__type__": "StringTableEntry",
   "__typeHash__": 3844612145,
   "szLabel": "Phase5Description",
   "szText": "Erys, Lort Zir ile ilgili daha çok şey öğrenebileceğimiz bir ayin biliyor. Önce Pis Kokulu Mozole'deki Kadim Vampirin kalıntılarını bulmalıyız.",
   "hLabel": 3388789226
  },
  {
   "__type__": "StringTableEntry",
   "__typeHash__": 3844612145,
   "szLabel": "Callback4Header",
   "szText": "{ITEM} edin",
   "hLabel": 3097634794
  },
  {
   "__type__": "StringTableEntry",
   "__typeHash__": 3844612145,
   "szLabel": "Phase11Description",
   "szText": "Kadim Vampir'in kalıntılarını ve canlandırmak için gerekli malzemeleri aldım. Nihayet Lort Zir hakkında daha fazla şey öğrenebiliriz. Erys'e dönmeliyim.",
   "hLabel": 1641010231
  },
  {
   "__type__": "StringTableEntry",
   "__typeHash__": 3844612145,
   "szLabel": "Callback10Header",
   "szText": "Ked Bardu'daki Erys'in yanına dön",
   "hLabel": 950701463
  },
  {
   "__type__": "StringTableEntry",
   "__typeHash__": 3844612145,
   "szLabel": "Callback50Header",
   "szText": "Sezon Yolculuğunun 2. Bölümünü tamamla",
   "hLabel": 3920748827
  }
 ],
 "ptMapStringTable": "0"
}
