{
 "__fileName__": "ptBR_Text/meta/StringList/Quest_QST_Step_South_AuguryofBones.stl",
 "__snoID__": 906546,
 "__type__": "StringListDefinition",
 "__typeHash__": 3672216444,
 "arStrings": [
  {
   "__type__": "StringTableEntry",
   "__typeHash__": 3844612145,
   "szLabel": "Name",
   "szText": "Augúrio dos Ossos",
   "hLabel": 4062401
  },
  {
   "__type__": "StringTableEntry",
   "__typeHash__": 3844612145,
   "szLabel": "Toast",
   "szText": "Os mortos ainda têm respostas para quem deseja indagar.",
   "hLabel": 141665387
  },
  {
   "__type__": "StringTableEntry",
   "__typeHash__": 3844612145,
   "szLabel": "Phase0Description",
   "szText": "Ogai, um eremita excêntrico, está tentando comungar com \"O Sorridente\", uma entidade antiga antes adorada nas Estepes. Ele pediu minha ajuda para obter poeira óssea dos antigos mortos, na esperança de falar com eles e conseguir respostas.",
   "hLabel": 3577478917
  },
  {
   "__type__": "StringTableEntry",
   "__typeHash__": 3844612145,
   "szLabel": "Callback12Header",
   "szText": "Colete poeira óssea de esqueletos no Vale dos Desgarrados ({DONE}/{NEEDED})",
   "hLabel": 3533637401
  },
  {
   "__type__": "StringTableEntry",
   "__typeHash__": 3844612145,
   "szLabel": "Phase8Description",
   "szText": "Moradores de Jirandai falaram de um eremita problemático que anda escavando os restos de seus antepassados honrados. Ele quer entrar em contato com \"O Sorridente\", uma entidade antes adorada nas Estepes.\r\n\r\nParece que ele está mexendo com algo perigoso. Preciso encontrá-lo no Vale dos Desgarrados.",
   "hLabel": 1557588493
  },
  {
   "__type__": "StringTableEntry",
   "__typeHash__": 3844612145,
   "szLabel": "Callback10Header",
   "szText": "Fale com Ogai no Vale dos Desgarrados",
   "hLabel": 950701463
  },
  {
   "__type__": "StringTableEntry",
   "__typeHash__": 3844612145,
   "szLabel": "Phase15Description",
   "szText": "Ogai, um eremita excêntrico, está tentando comungar com \"O Sorridente\", uma entidade antiga antes adorada nas Estepes. Ele pediu minha ajuda para obter poeira óssea dos antigos mortos, na esperança de falar com eles e conseguir respostas.",
   "hLabel": 631065019
  },
  {
   "__type__": "StringTableEntry",
   "__typeHash__": 3844612145,
   "szLabel": "Callback17Header",
   "szText": "Volte até Ogai",
   "hLabel": 1401042654
  },
  {
   "__type__": "StringTableEntry",
   "__typeHash__": 3844612145,
   "szLabel": "Phase18Description",
   "szText": "Ogai inalou a poeira óssea que coletei e entrou em transe. Sua fala estava entrecortada e confusa, mas surtiu efeito. Suas palavras revelaram uma inscrição oculta, e ele deu um forte espirro. Por mais estranho que sejam, talvez suas ideias tenham algum fundamento.",
   "hLabel": 3094831582
  },
  {
   "__type__": "StringTableEntry",
   "__typeHash__": 3844612145,
   "szLabel": "Callback20Header",
   "szText": "Investigue a Inscrição Imemorial",
   "hLabel": 619471480
  },
  {
   "__type__": "StringTableEntry",
   "__typeHash__": 3844612145,
   "szLabel": "Phase21Description",
   "szText": "Ogai inalou a poeira óssea que coletei e entrou em transe. Sua fala estava entrecortada e confusa, mas surtiu efeito. Suas palavras revelaram uma inscrição oculta, e ele deu um forte espirro. Por mais estranho que sejam, talvez suas ideias tenham algum fundamento.",
   "hLabel": 2972638648
  },
  {
   "__type__": "StringTableEntry",
   "__typeHash__": 3844612145,
   "szLabel": "Callback23Header",
   "szText": "Fale com Ogai sobre a Inscrição Ancestral",
   "hLabel": 198908091
  }
 ],
 "ptMapStringTable": "0"
}
