{
 "__fileName__": "ptBR_Text/meta/StringList/Quest_DSQ_Hawe_Coast_Lyndon_03_Cellar.stl",
 "__snoID__": 1266427,
 "__type__": "StringListDefinition",
 "__typeHash__": 3672216444,
 "arStrings": [
  {
   "__type__": "StringTableEntry",
   "__typeHash__": 3844612145,
   "szLabel": "Name",
   "szText": "Pego em Flagrante",
   "hLabel": 4062401
  },
  {
   "__type__": "StringTableEntry",
   "__typeHash__": 3844612145,
   "szLabel": "Toast",
   "szText": "Orton é o traidor.",
   "hLabel": 141665387
  },
  {
   "__type__": "StringTableEntry",
   "__typeHash__": 3844612145,
   "szLabel": "Callback2Header",
   "szText": "Entre no Porão de Armazenamento de Remanso",
   "hLabel": 514698856
  },
  {
   "__type__": "StringTableEntry",
   "__typeHash__": 3844612145,
   "szLabel": "Callback29Header",
   "szText": "Acabe com a emboscada de Orton",
   "hLabel": 3652748609
  },
  {
   "__type__": "StringTableEntry",
   "__typeHash__": 3844612145,
   "szLabel": "Callback31Header",
   "szText": "Mate Orton",
   "hLabel": 1579709466
  },
  {
   "__type__": "StringTableEntry",
   "__typeHash__": 3844612145,
   "szLabel": "Callback36Header",
   "szText": "Esconda-se atrás dos caixotes",
   "hLabel": 3742082015
  },
  {
   "__type__": "StringTableEntry",
   "__typeHash__": 3844612145,
   "szLabel": "Callback40Header",
   "szText": "Mate Orton",
   "hLabel": 4251978810
  },
  {
   "__type__": "StringTableEntry",
   "__typeHash__": 3844612145,
   "szLabel": "Phase0Description",
   "szText": "Lyndon pediu para eu encontrá-lo no porão de armazenamento em Remanso. Ele está planejando confrontar Orton lá.",
   "hLabel": 3577478917
  },
  {
   "__type__": "StringTableEntry",
   "__typeHash__": 3844612145,
   "szLabel": "Phase30Description",
   "szText": "Orton não gostava de diplomacia. Ele criou sua própria emboscada. Lyndon e eu precisamos matar Orton e sua equipe de traidores.",
   "hLabel": 3483011544
  },
  {
   "__type__": "StringTableEntry",
   "__typeHash__": 3844612145,
   "szLabel": "Phase34Description",
   "szText": "Lyndon convidou Orton na esperança de lidar com isso diplomaticamente. Mas caso as coisas deem errado, ele pediu para eu me esconder.",
   "hLabel": 2473066332
  },
  {
   "__type__": "StringTableEntry",
   "__typeHash__": 3844612145,
   "szLabel": "Phase46Description",
   "szText": "Lyndon pediu para eu encontrá-lo no porão de armazenamento em Remanso. Ele está planejando confrontar Orton lá.",
   "hLabel": 1152238495
  },
  {
   "__type__": "StringTableEntry",
   "__typeHash__": 3844612145,
   "szLabel": "Callback48Header",
   "szText": "Fale com Lyndon",
   "hLabel": 1698820674
  }
 ],
 "ptMapStringTable": "0"
}
