{
 "__fileName__": "jaJP_Text/meta/StringList/Conv_Lorebook_DGN_Step_24.stl",
 "__snoID__": 725779,
 "__type__": "StringListDefinition",
 "__typeHash__": 3672216444,
 "arStrings": [
  {
   "__type__": "StringTableEntry",
   "__typeHash__": 3844612145,
   "szLabel": "MenuLabel",
   "szText": "僧侶の日誌",
   "hLabel": 4215274549
  },
  {
   "__type__": "StringTableEntry",
   "__typeHash__": 3844612145,
   "szLabel": "DisembodiedVoice",
   "szText": "僧侶の日誌",
   "hLabel": 155764431
  },
  {
   "__type__": "StringTableEntry",
   "__typeHash__": 3844612145,
   "szLabel": "Line1.E761C",
   "szText": "さらに調べていくと、疑いは確信に変わった。オーベイは、既存の建物の上に建てられていたのだ。現存する記録によると、修道院のこの隠された一画は、ザカラムの審問と何らかの関係があるらしい。",
   "hLabel": 1566127917
  },
  {
   "__type__": "StringTableEntry",
   "__typeHash__": 3844612145,
   "szLabel": "Line5.E761C",
   "szText": "数十年前、彼らはこの地方にやってきて、地元の人々を服従させたのだ。信仰を受け入れない者は拷問され、埋葬されたらしい。だとしたら、我々の下にある建造物は集落の遺跡、あるいは彼らの墓かもしれない。",
   "hLabel": 2437032497
  },
  {
   "__type__": "StringTableEntry",
   "__typeHash__": 3844612145,
   "szLabel": "Line3.E761C",
   "szText": "すぐにわかる。私は内なる道を見つけた。ザカラムの真の信条を体現するためには、黒歴史に立ち向かわなければならない。",
   "hLabel": 4149063855
  },
  {
   "__type__": "StringTableEntry",
   "__typeHash__": 3844612145,
   "szLabel": "Line1.E761C.F",
   "szText": "さらに調べていくと、疑いは確信に変わった。オーベイは、既存の建物の上に建てられていたのだ。現存する記録によると、修道院のこの隠された一画は、ザカラムの審問と何らかの関係があるらしい。",
   "hLabel": 411286721
  },
  {
   "__type__": "StringTableEntry",
   "__typeHash__": 3844612145,
   "szLabel": "Line3.E761C.F",
   "szText": "すぐにわかる。私は内なる道を見つけた。ザカラムの真の信条を体現するためには、黒歴史に立ち向かわなければならない。",
   "hLabel": 24944323
  },
  {
   "__type__": "StringTableEntry",
   "__typeHash__": 3844612145,
   "szLabel": "Line5.E761C.F",
   "szText": "数十年前、彼らはこの地方にやってきて、地元の人々を服従させたのだ。信仰を受け入れない者は拷問され、埋葬されたらしい。だとしたら、我々の下にある建造物は集落の遺跡、あるいは彼らの墓かもしれない。",
   "hLabel": 3933569221
  }
 ],
 "ptMapStringTable": "0"
}
