{
 "__fileName__": "ruRU_Text/meta/StringList/Affix_Pants_Unique_Rogue_004.stl",
 "__snoID__": 1106490,
 "__type__": "StringListDefinition",
 "__typeHash__": 3672216444,
 "arStrings": [
  {
   "__type__": "StringTableEntry",
   "__typeHash__": 3844612145,
   "szLabel": "Desc",
   "szText": "{c_important}\"Смертоносная ловушка\"{/c} наносит на {c_random}[Affix_Value_1|%x|]{/c} больше урона. Если {c_important}\"Смертоносная ловушка\"{/c} не поражает босса или другого игрока, она автоматически взводится заново, пока не убьет противника. ",
   "hLabel": 3707583
  }
 ],
 "ptMapStringTable": "0"
}
