{
 "__fileName__": "data/ruRU_Text/meta/StringList/Conv_QST_Step_Guulrahn_Trader_OPT.stl",
 "__snoID__": 1062558,
 "__type__": "StringListDefinition",
 "__typeHash__": 3672216444,
 "arStrings": [
  {
   "__type__": "StringTableEntry",
   "__typeHash__": 3844612145,
   "szLabel": "MenuLabel",
   "szText": "\"Что здесь произошло?\"",
   "hLabel": 4215274549
  },
  {
   "__type__": "StringTableEntry",
   "__typeHash__": 3844612145,
   "szLabel": "Line11.EECAD",
   "szText": "Тиран Брол и его проклятые каннибалы. Они ворвались в город, как дикие звери. У стражей не было ни шанса.",
   "hLabel": 1920866890
  },
  {
   "__type__": "StringTableEntry",
   "__typeHash__": 3844612145,
   "szLabel": "Line11.EECAD.F",
   "szText": "Тиран Брол и его проклятые каннибалы. Они ворвались в город, как дикие звери. У стражей не было ни шанса.",
   "hLabel": 174971678
  }
 ],
 "ptMapStringTable": "0"
}
