{
 "__fileName__": "ruRU_Text/meta/StringList/Conv_TWN_Scos_Marowen_FMR_G01.stl",
 "__snoID__": 1050976,
 "__type__": "StringListDefinition",
 "__typeHash__": 3672216444,
 "arStrings": [
  {
   "__type__": "StringTableEntry",
   "__typeHash__": 3844612145,
   "szLabel": "MenuLabel",
   "szText": "\"Как поживает стадо?\"",
   "hLabel": 4215274549
  },
  {
   "__type__": "StringTableEntry",
   "__typeHash__": 3844612145,
   "szLabel": "Line1.10094C",
   "szText": "Овцы все блеют и блеют. Должно быть, к дождю и ветру.",
   "hLabel": 2394030760
  },
  {
   "__type__": "StringTableEntry",
   "__typeHash__": 3844612145,
   "szLabel": "Line1.10094C.F",
   "szText": "Овцы все блеют и блеют. Должно быть, к дождю и ветру.",
   "hLabel": 54350588
  }
 ],
 "ptMapStringTable": "0"
}
