{
 "__fileName__": "ruRU_Text/meta/StringList/Quest_QST_Frac_Lilith_Blood_02.stl",
 "__snoID__": 1455735,
 "__type__": "StringListDefinition",
 "__typeHash__": 3672216444,
 "arStrings": [
  {
   "__type__": "StringTableEntry",
   "__typeHash__": 3844612145,
   "szLabel": "Toast",
   "szText": "Верните Вошалко символ благосклонности Инария.",
   "hLabel": 141665387
  },
  {
   "__type__": "StringTableEntry",
   "__typeHash__": 3844612145,
   "szLabel": "Name",
   "szText": "Покров Отца",
   "hLabel": 4062401
  },
  {
   "__type__": "StringTableEntry",
   "__typeHash__": 3844612145,
   "szLabel": "Phase0Description",
   "szText": "Чтобы изгнать Лилит из моего тела, Вошалко нужна забытая реликвия церкви: плацента плода. Он сказал, что ее можно найти где-то в Краю милосердия.",
   "hLabel": 3577478917
  },
  {
   "__type__": "StringTableEntry",
   "__typeHash__": 3844612145,
   "szLabel": "Callback5Header",
   "szText": "Найдите предмет: {ITEM}",
   "hLabel": 94135467
  },
  {
   "__type__": "StringTableEntry",
   "__typeHash__": 3844612145,
   "szLabel": "Phase8Description",
   "szText": "Плацента плода у меня, теперь нужно ее вернуть. Вошалко ждет меня в Киовашаде.",
   "hLabel": 1557588493
  },
  {
   "__type__": "StringTableEntry",
   "__typeHash__": 3844612145,
   "szLabel": "Callback7Header",
   "szText": "Найдите Вошалко в Киовашаде",
   "hLabel": 2677071405
  }
 ],
 "ptMapStringTable": "0"
}
