{
 "__fileName__": "itIT_Text/meta/StringList/Conv_QST_Frac_CriesInn_Vendral_03.stl",
 "__snoID__": 1059267,
 "__type__": "StringListDefinition",
 "__typeHash__": 3672216444,
 "arStrings": [
  {
   "__type__": "StringTableEntry",
   "__typeHash__": 3844612145,
   "szLabel": "MenuLabel",
   "szText": "\"Cosa sai dirmi sul Manicomio Nero?\"",
   "hLabel": 4215274549
  },
  {
   "__type__": "StringTableEntry",
   "__typeHash__": 3844612145,
   "szLabel": "Line1.1029AF",
   "szText": "Quando scoprirono cosa aveva fatto, lo misero in catene e lo portarono al Manicomio Nero.",
   "hLabel": 2394104122
  },
  {
   "__type__": "StringTableEntry",
   "__typeHash__": 3844612145,
   "szLabel": "Line3.1029AF",
   "szText": "Anni dopo, il manicomio fu abbandonato. I più fortunati morirono di fame, gli altri fuggirono dalle celle per lottare tra loro.",
   "hLabel": 1731644156
  },
  {
   "__type__": "StringTableEntry",
   "__typeHash__": 3844612145,
   "szLabel": "Line5.1029AF",
   "szText": "Fu una morte atroce, non mi stupisce che alcuni si siano rifiutati di andarsene.",
   "hLabel": 1069184190
  },
  {
   "__type__": "StringTableEntry",
   "__typeHash__": 3844612145,
   "szLabel": "Line1.1029AF.F",
   "szText": "Quando scoprirono cosa aveva fatto, lo misero in catene e lo portarono al Manicomio Nero.",
   "hLabel": 134241806
  },
  {
   "__type__": "StringTableEntry",
   "__typeHash__": 3844612145,
   "szLabel": "Line3.1029AF.F",
   "szText": "Anni dopo, il manicomio fu abbandonato. I più fortunati morirono di fame, gli altri fuggirono dalle celle per lottare tra loro.",
   "hLabel": 269844560
  },
  {
   "__type__": "StringTableEntry",
   "__typeHash__": 3844612145,
   "szLabel": "Line5.1029AF.F",
   "szText": "Fu una morte atroce, non mi stupisce che alcuni si siano rifiutati di andarsene.",
   "hLabel": 405447314
  }
 ],
 "ptMapStringTable": "0"
}
