{
 "__fileName__": "itIT_Text/meta/StringList/EndGameNotify.stl",
 "__snoID__": 565342,
 "__type__": "StringListDefinition",
 "__typeHash__": 3672216444,
 "arStrings": [
  {
   "__type__": "StringTableEntry",
   "__typeHash__": 3844612145,
   "szLabel": "AspectUnlock_KBM",
   "szText": "Hai sbloccato: {c_highlight}{s1}{/c}! Clicca su {hotkey:Collections} per visualizzarlo nel {c_highlight}Codex del potere{/c}.",
   "hLabel": 1933100485
  },
  {
   "__type__": "StringTableEntry",
   "__typeHash__": 3844612145,
   "szLabel": "AspectUnlock_Controller",
   "szText": "Hai sbloccato: {c_highlight}{s1}{/c}! Clicca su {hotkey:Map} per visualizzarlo nel {c_highlight}Codex del potere{/c}.",
   "hLabel": 3310768111
  },
  {
   "__type__": "StringTableEntry",
   "__typeHash__": 3844612145,
   "szLabel": "LeaveNow",
   "szText": "Esci",
   "hLabel": 4115971201
  },
  {
   "__type__": "StringTableEntry",
   "__typeHash__": 3844612145,
   "szLabel": "ReturnToEntrance",
   "szText": "Tornerai all'entrata tra {c_highlight}{s1} s{/c}",
   "hLabel": 3417462195
  },
  {
   "__type__": "StringTableEntry",
   "__typeHash__": 3844612145,
   "szLabel": "KeyedDungeonFailureReason",
   "szText": "Resurrezioni esaurite",
   "hLabel": 2537536754
  },
  {
   "__type__": "StringTableEntry",
   "__typeHash__": 3844612145,
   "szLabel": "KeyedDungeonFailure",
   "szText": "Spedizione da Incubo fallita",
   "hLabel": 743397930
  },
  {
   "__type__": "StringTableEntry",
   "__typeHash__": 3844612145,
   "szLabel": "LeaveNow_Controller",
   "szText": "{icon:button4, 2.0} Esci",
   "hLabel": 3811210692
  },
  {
   "__type__": "StringTableEntry",
   "__typeHash__": 3844612145,
   "szLabel": "KeyedDungeonComplete",
   "szText": "Spedizione da Incubo completata",
   "hLabel": 817648507
  },
  {
   "__type__": "StringTableEntry",
   "__typeHash__": 3844612145,
   "szLabel": "DungeonComplete",
   "szText": "Spedizione completata",
   "hLabel": 3640820073
  },
  {
   "__type__": "StringTableEntry",
   "__typeHash__": 3844612145,
   "szLabel": "RewardsCompletion",
   "szText": "Ricompense completamento",
   "hLabel": 1248862738
  },
  {
   "__type__": "StringTableEntry",
   "__typeHash__": 3844612145,
   "szLabel": "RewardsTrial",
   "szText": "Ricompense prova",
   "hLabel": 3385364660
  },
  {
   "__type__": "StringTableEntry",
   "__typeHash__": 3844612145,
   "szLabel": "CellarComplete",
   "szText": "Cantina completata",
   "hLabel": 1340594956
  },
  {
   "__type__": "StringTableEntry",
   "__typeHash__": 3844612145,
   "szLabel": "VesselOfHatredComplete",
   "szText": "Ricettacolo dell'Odio",
   "hLabel": 3442937080
  },
  {
   "__type__": "StringTableEntry",
   "__typeHash__": 3844612145,
   "szLabel": "VesselOfHatredSubheader",
   "szText": "Evento completato",
   "hLabel": 3816798034
  }
 ],
 "ptMapStringTable": "0"
}
