{
 "__fileName__": "data/deDE_Text/meta/StringList/Conv_QST_Scos_LochRaeth_Orphan_02.stl",
 "__snoID__": 1037321,
 "__type__": "StringListDefinition",
 "__typeHash__": 3672216444,
 "arStrings": [
  {
   "__type__": "StringTableEntry",
   "__typeHash__": 3844612145,
   "szLabel": "MenuLabel",
   "szText": "\"Seid Ihr Padrig?\"",
   "hLabel": 4215274549
  },
  {
   "__type__": "StringTableEntry",
   "__typeHash__": 3844612145,
   "szLabel": "Line38.FD0E3",
   "szText": "Wer will das wissen? Ah … Entschuldigt, Wanderer. Braucht Ihr etwas?",
   "hLabel": 1709842643
  },
  {
   "__type__": "StringTableEntry",
   "__typeHash__": 3844612145,
   "szLabel": "Line14.FD0E3",
   "szText": "Was ist das? Ein Brief? \"… diese Worte erreichen dich vielleicht nie …\" Nein. Nein, nein, nein. Wo habt Ihr den her?",
   "hLabel": 1501398029
  },
  {
   "__type__": "StringTableEntry",
   "__typeHash__": 3844612145,
   "szLabel": "Line16.FD0E3",
   "szText": "\"Die Ertrunkenen kommen immer näher …\" Und die ganze Zeit habe ich mich für meinen Vater geschämt. Ich dachte, er hätte uns verlassen.",
   "hLabel": 4084333967
  },
  {
   "__type__": "StringTableEntry",
   "__typeHash__": 3844612145,
   "szLabel": "Line28.FD0E3",
   "szText": "Und das? Halt – so etwas habe ich schon einmal gesehen. Ein mit druidischer Macht erfülltes Amulett.",
   "hLabel": 2041072626
  },
  {
   "__type__": "StringTableEntry",
   "__typeHash__": 3844612145,
   "szLabel": "Line30.FD0E3",
   "szText": "Das ist ein Relikt … aus meiner Kindheit, als unser Volk noch die alten Sitten praktizierte. Aber ich fürchte, ich habe nicht die Fähigkeit, es zu benutzen.",
   "hLabel": 4263000779
  },
  {
   "__type__": "StringTableEntry",
   "__typeHash__": 3844612145,
   "szLabel": "Line32.FD0E3",
   "szText": "Aber vielleicht … Könntet Ihr es benutzen? Mein Vater hätte nicht gewollt, dass es auf einem Regal Staub ansammelt.",
   "hLabel": 2550969421
  },
  {
   "__type__": "StringTableEntry",
   "__typeHash__": 3844612145,
   "szLabel": "Line34.FD0E3",
   "szText": "Ich wünschte, Mutter wäre hier, um es zu sehen … Nun, wenigstens kann ihr Geist jetzt in Frieden ruhen. Danke, mein Freund.",
   "hLabel": 838938063
  },
  {
   "__type__": "StringTableEntry",
   "__typeHash__": 3844612145,
   "szLabel": "Canned_Line28.BAE4.Bar.F",
   "szText": "Tut mir leid.",
   "hLabel": 2597837883
  },
  {
   "__type__": "StringTableEntry",
   "__typeHash__": 3844612145,
   "szLabel": "Canned_Line28.BAE4.Bar.M",
   "szText": "Tut mir leid.",
   "hLabel": 2597837890
  },
  {
   "__type__": "StringTableEntry",
   "__typeHash__": 3844612145,
   "szLabel": "Canned_Line28.BAE4.Dru.F",
   "szText": "Tut mir leid.",
   "hLabel": 2600823921
  },
  {
   "__type__": "StringTableEntry",
   "__typeHash__": 3844612145,
   "szLabel": "Canned_Line28.BAE4.Dru.M",
   "szText": "Tut mir leid.",
   "hLabel": 2600823928
  },
  {
   "__type__": "StringTableEntry",
   "__typeHash__": 3844612145,
   "szLabel": "Canned_Line28.BAE4.Nec.F",
   "szText": "Tut mir leid.",
   "hLabel": 2612196348
  },
  {
   "__type__": "StringTableEntry",
   "__typeHash__": 3844612145,
   "szLabel": "Canned_Line28.BAE4.Nec.M",
   "szText": "Tut mir leid.",
   "hLabel": 2612196355
  },
  {
   "__type__": "StringTableEntry",
   "__typeHash__": 3844612145,
   "szLabel": "Canned_Line28.BAE4.Rog.F",
   "szText": "Tut mir leid.",
   "hLabel": 2617303758
  },
  {
   "__type__": "StringTableEntry",
   "__typeHash__": 3844612145,
   "szLabel": "Canned_Line28.BAE4.Rog.M",
   "szText": "Tut mir leid.",
   "hLabel": 2617303765
  },
  {
   "__type__": "StringTableEntry",
   "__typeHash__": 3844612145,
   "szLabel": "Canned_Line28.BAE4.Sor.F",
   "szText": "Tut mir leid.",
   "hLabel": 2618501658
  },
  {
   "__type__": "StringTableEntry",
   "__typeHash__": 3844612145,
   "szLabel": "Canned_Line28.BAE4.Sor.M",
   "szText": "Tut mir leid.",
   "hLabel": 2618501665
  },
  {
   "__type__": "StringTableEntry",
   "__typeHash__": 3844612145,
   "szLabel": "Canned_Line34.BAE4.Bar.F",
   "szText": "Ich glaube, das gehört Euch.",
   "hLabel": 644444216
  },
  {
   "__type__": "StringTableEntry",
   "__typeHash__": 3844612145,
   "szLabel": "Canned_Line34.BAE4.Bar.M",
   "szText": "Ich glaube, das gehört Euch.",
   "hLabel": 644444223
  },
  {
   "__type__": "StringTableEntry",
   "__typeHash__": 3844612145,
   "szLabel": "Canned_Line34.BAE4.Dru.F",
   "szText": "Ich glaube, das gehört Euch.",
   "hLabel": 647430254
  },
  {
   "__type__": "StringTableEntry",
   "__typeHash__": 3844612145,
   "szLabel": "Canned_Line34.BAE4.Dru.M",
   "szText": "Ich glaube, das gehört Euch.",
   "hLabel": 647430261
  },
  {
   "__type__": "StringTableEntry",
   "__typeHash__": 3844612145,
   "szLabel": "Canned_Line34.BAE4.Nec.F",
   "szText": "Ich bin sicher, das gehört Euch.",
   "hLabel": 658802681
  },
  {
   "__type__": "StringTableEntry",
   "__typeHash__": 3844612145,
   "szLabel": "Canned_Line34.BAE4.Nec.M",
   "szText": "Ich bin sicher, das gehört Euch.",
   "hLabel": 658802688
  },
  {
   "__type__": "StringTableEntry",
   "__typeHash__": 3844612145,
   "szLabel": "Canned_Line34.BAE4.Rog.F",
   "szText": "Ich glaube, das gehört Euch.",
   "hLabel": 663910091
  },
  {
   "__type__": "StringTableEntry",
   "__typeHash__": 3844612145,
   "szLabel": "Canned_Line34.BAE4.Rog.M",
   "szText": "Ich glaube, das gehört Euch.",
   "hLabel": 663910098
  },
  {
   "__type__": "StringTableEntry",
   "__typeHash__": 3844612145,
   "szLabel": "Canned_Line34.BAE4.Sor.F",
   "szText": "Das gehört wohl Euch.",
   "hLabel": 665107991
  },
  {
   "__type__": "StringTableEntry",
   "__typeHash__": 3844612145,
   "szLabel": "Canned_Line34.BAE4.Sor.M",
   "szText": "Das gehört wohl Euch.",
   "hLabel": 665107998
  },
  {
   "__type__": "StringTableEntry",
   "__typeHash__": 3844612145,
   "szLabel": "Canned_Line7.BAE4.Bar.F",
   "szText": "Sorgt Euch nicht, ich kümmere mich darum.",
   "hLabel": 206268840
  },
  {
   "__type__": "StringTableEntry",
   "__typeHash__": 3844612145,
   "szLabel": "Canned_Line7.BAE4.Bar.M",
   "szText": "Sorgt Euch nicht, ich kümmere mich darum.",
   "hLabel": 206268847
  },
  {
   "__type__": "StringTableEntry",
   "__typeHash__": 3844612145,
   "szLabel": "Canned_Line7.BAE4.Dru.F",
   "szText": "Sorgt Euch nicht, ich kümmere mich darum.",
   "hLabel": 209254878
  },
  {
   "__type__": "StringTableEntry",
   "__typeHash__": 3844612145,
   "szLabel": "Canned_Line7.BAE4.Dru.M",
   "szText": "Sorgt Euch nicht, ich kümmere mich darum.",
   "hLabel": 209254885
  },
  {
   "__type__": "StringTableEntry",
   "__typeHash__": 3844612145,
   "szLabel": "Canned_Line7.BAE4.Nec.F",
   "szText": "Sorgt Euch nicht, ich kümmere mich darum.",
   "hLabel": 220627305
  },
  {
   "__type__": "StringTableEntry",
   "__typeHash__": 3844612145,
   "szLabel": "Canned_Line7.BAE4.Nec.M",
   "szText": "Sorgt Euch nicht, ich kümmere mich darum.",
   "hLabel": 220627312
  },
  {
   "__type__": "StringTableEntry",
   "__typeHash__": 3844612145,
   "szLabel": "Canned_Line7.BAE4.Rog.F",
   "szText": "Sorgt Euch nicht, ich kümmere mich darum.",
   "hLabel": 225734715
  },
  {
   "__type__": "StringTableEntry",
   "__typeHash__": 3844612145,
   "szLabel": "Canned_Line7.BAE4.Rog.M",
   "szText": "Sorgt Euch nicht, ich kümmere mich darum.",
   "hLabel": 225734722
  },
  {
   "__type__": "StringTableEntry",
   "__typeHash__": 3844612145,
   "szLabel": "Canned_Line7.BAE4.Sor.F",
   "szText": "Sorgt Euch nicht, ich kümmere mich darum.",
   "hLabel": 226932615
  },
  {
   "__type__": "StringTableEntry",
   "__typeHash__": 3844612145,
   "szLabel": "Canned_Line7.BAE4.Sor.M",
   "szText": "Sorgt Euch nicht, ich kümmere mich darum.",
   "hLabel": 226932622
  },
  {
   "__type__": "StringTableEntry",
   "__typeHash__": 3844612145,
   "szLabel": "Line14.FD0E3.F",
   "szText": "Was ist das? Ein Brief? \"… diese Worte erreichen dich vielleicht nie …\" Nein. Nein, nein, nein. Wo habt Ihr den her?",
   "hLabel": 2934882721
  },
  {
   "__type__": "StringTableEntry",
   "__typeHash__": 3844612145,
   "szLabel": "Line16.FD0E3.F",
   "szText": "\"Die Ertrunkenen kommen immer näher …\" Und die ganze Zeit habe ich mich für meinen Vater geschämt. Ich dachte, er hätte uns verlassen.",
   "hLabel": 2548540323
  },
  {
   "__type__": "StringTableEntry",
   "__typeHash__": 3844612145,
   "szLabel": "Line28.FD0E3.F",
   "szText": "Und das? Halt – so etwas habe ich schon einmal gesehen. Ein mit druidischer Macht erfülltes Amulett.",
   "hLabel": 2229999302
  },
  {
   "__type__": "StringTableEntry",
   "__typeHash__": 3844612145,
   "szLabel": "Line30.FD0E3.F",
   "szText": "Das ist ein Relikt … aus meiner Kindheit, als unser Volk noch die alten Sitten praktizierte. Aber ich fürchte, ich habe nicht die Fähigkeit, es zu benutzen.",
   "hLabel": 3843170271
  },
  {
   "__type__": "StringTableEntry",
   "__typeHash__": 3844612145,
   "szLabel": "Line32.FD0E3.F",
   "szText": "Aber vielleicht … Könntet Ihr es benutzen? Mein Vater hätte nicht gewollt, dass es auf einem Regal Staub ansammelt.",
   "hLabel": 3456827873
  },
  {
   "__type__": "StringTableEntry",
   "__typeHash__": 3844612145,
   "szLabel": "Line34.FD0E3.F",
   "szText": "Ich wünschte, Mutter wäre hier, um es zu sehen … Nun, wenigstens kann ihr Geist jetzt in Frieden ruhen. Danke, meine Freundin.",
   "hLabel": 3070485475
  },
  {
   "__type__": "StringTableEntry",
   "__typeHash__": 3844612145,
   "szLabel": "Line38.FD0E3.F",
   "szText": "Wer will das wissen? Ah … Entschuldigt, Wanderin. Braucht Ihr etwas?",
   "hLabel": 2297800679
  }
 ],
 "ptMapStringTable": "0"
}
