{
 "__fileName__": "zhCN_Text/meta/StringList/Conv_QST_S03_Main_03_Scos_020.stl",
 "__snoID__": 1632950,
 "__type__": "StringListDefinition",
 "__typeHash__": 3672216444,
 "arStrings": [
  {
   "__type__": "StringTableEntry",
   "__typeHash__": 3844612145,
   "szLabel": "MenuLabel",
   "szText": "Canned Player Dialogue",
   "hLabel": 4215274549
  },
  {
   "__type__": "StringTableEntry",
   "__typeHash__": 3844612145,
   "szLabel": "Canned_FoundThing_Line32.BAE4.Bar.F",
   "szText": "肯定就是它了。",
   "hLabel": 4024305291
  },
  {
   "__type__": "StringTableEntry",
   "__typeHash__": 3844612145,
   "szLabel": "Canned_FoundThing_Line32.BAE4.Bar.M",
   "szText": "肯定就是它了。",
   "hLabel": 4024305298
  },
  {
   "__type__": "StringTableEntry",
   "__typeHash__": 3844612145,
   "szLabel": "Canned_FoundThing_Line32.BAE4.Dru.F",
   "szText": "肯定就是它了。",
   "hLabel": 4027291329
  },
  {
   "__type__": "StringTableEntry",
   "__typeHash__": 3844612145,
   "szLabel": "Canned_FoundThing_Line32.BAE4.Dru.M",
   "szText": "肯定就是它了。",
   "hLabel": 4027291336
  },
  {
   "__type__": "StringTableEntry",
   "__typeHash__": 3844612145,
   "szLabel": "Canned_FoundThing_Line32.BAE4.Nec.F",
   "szText": "肯定就是它了。",
   "hLabel": 4038663756
  },
  {
   "__type__": "StringTableEntry",
   "__typeHash__": 3844612145,
   "szLabel": "Canned_FoundThing_Line32.BAE4.Nec.M",
   "szText": "肯定就是它了。",
   "hLabel": 4038663763
  },
  {
   "__type__": "StringTableEntry",
   "__typeHash__": 3844612145,
   "szLabel": "Canned_FoundThing_Line32.BAE4.Rog.F",
   "szText": "肯定就是它了。",
   "hLabel": 4043771166
  },
  {
   "__type__": "StringTableEntry",
   "__typeHash__": 3844612145,
   "szLabel": "Canned_FoundThing_Line32.BAE4.Rog.M",
   "szText": "肯定就是它了。",
   "hLabel": 4043771173
  },
  {
   "__type__": "StringTableEntry",
   "__typeHash__": 3844612145,
   "szLabel": "Canned_FoundThing_Line32.BAE4.Sor.F",
   "szText": "肯定就是它了。",
   "hLabel": 4044969066
  },
  {
   "__type__": "StringTableEntry",
   "__typeHash__": 3844612145,
   "szLabel": "Canned_FoundThing_Line32.BAE4.Sor.M",
   "szText": "肯定就是它了。",
   "hLabel": 4044969073
  }
 ],
 "ptMapStringTable": "0"
}
