{
 "__fileName__": "zhCN_Text/meta/StringList/Quest_QST_Frac_Underworld_03.stl",
 "__snoID__": 486211,
 "__type__": "StringListDefinition",
 "__typeHash__": 3672216444,
 "arStrings": [
  {
   "__type__": "StringTableEntry",
   "__typeHash__": 3844612145,
   "szLabel": "Name",
   "szText": "进入大门",
   "hLabel": 4062401
  },
  {
   "__type__": "StringTableEntry",
   "__typeHash__": 3844612145,
   "szLabel": "Toast",
   "szText": "在安眠地寻找莉莉丝和维纳德的踪迹",
   "hLabel": 141665387
  },
  {
   "__type__": "StringTableEntry",
   "__typeHash__": 3844612145,
   "szLabel": "BreadcrumbHeader",
   "szText": "在安眠地寻找莉莉丝和维纳德的踪迹",
   "hLabel": 2596636736
  },
  {
   "__type__": "StringTableEntry",
   "__typeHash__": 3844612145,
   "szLabel": "BreadcrumbDescription",
   "szText": "我和蕾蕊儿必须深入上古之城卡萨玛内的安眠地。只有这样，我们才能继续追寻莉莉丝和蕾蕊儿的母亲维纳德的踪迹。",
   "hLabel": 4222796379
  },
  {
   "__type__": "StringTableEntry",
   "__typeHash__": 3844612145,
   "szLabel": "Phase96Description",
   "szText": "我和蕾蕊儿深入上古之城卡萨玛，穿过安眠地的黑暗通道，追寻莉莉丝和维纳德的踪迹。",
   "hLabel": 3515413284
  },
  {
   "__type__": "StringTableEntry",
   "__typeHash__": 3844612145,
   "szLabel": "Phase96OutsideSubzoneHeader",
   "szText": "追寻莉莉丝和维纳德的踪迹前往哀恸之滨",
   "hLabel": 780722412
  },
  {
   "__type__": "StringTableEntry",
   "__typeHash__": 3844612145,
   "szLabel": "Callback225Header",
   "szText": "追寻莉莉丝和维纳德的踪迹前往哀恸之滨",
   "hLabel": 1281913359
  },
  {
   "__type__": "StringTableEntry",
   "__typeHash__": 3844612145,
   "szLabel": "Phase121Description",
   "szText": "我和蕾蕊儿深入上古之城卡萨玛，穿过安眠地的黑暗通道，追寻莉莉丝和维纳德的踪迹。",
   "hLabel": 2162053033
  },
  {
   "__type__": "StringTableEntry",
   "__typeHash__": 3844612145,
   "szLabel": "Phase121OutsideSubzoneHeader",
   "szText": "和蕾蕊儿一起追寻莉莉丝和维纳德的踪迹",
   "hLabel": 3542295313
  },
  {
   "__type__": "StringTableEntry",
   "__typeHash__": 3844612145,
   "szLabel": "Callback236Header",
   "szText": "与蕾蕊儿交谈",
   "hLabel": 2242151345
  },
  {
   "__type__": "StringTableEntry",
   "__typeHash__": 3844612145,
   "szLabel": "Phase140Description",
   "szText": "我和蕾蕊儿深入上古之城卡萨玛，穿过安眠地的黑暗通道，追寻莉莉丝和维纳德的踪迹。",
   "hLabel": 4004054346
  },
  {
   "__type__": "StringTableEntry",
   "__typeHash__": 3844612145,
   "szLabel": "Phase140OutsideSubzoneHeader",
   "szText": "和蕾蕊儿一起追寻莉莉丝和维纳德的踪迹",
   "hLabel": 1735310802
  },
  {
   "__type__": "StringTableEntry",
   "__typeHash__": 3844612145,
   "szLabel": "Callback139Header",
   "szText": "和蕾蕊儿一起追寻莉莉丝和维纳德的踪迹",
   "hLabel": 4162242803
  },
  {
   "__type__": "StringTableEntry",
   "__typeHash__": 3844612145,
   "szLabel": "Phase241Description",
   "szText": "我和蕾蕊儿深入上古之城卡萨玛，穿过安眠地的黑暗通道，追寻莉莉丝和维纳德的踪迹。",
   "hLabel": 1524407372
  },
  {
   "__type__": "StringTableEntry",
   "__typeHash__": 3844612145,
   "szLabel": "Phase241OutsideSubzoneHeader",
   "szText": "和蕾蕊儿一起追寻莉莉丝和维纳德的踪迹",
   "hLabel": 2159105812
  },
  {
   "__type__": "StringTableEntry",
   "__typeHash__": 3844612145,
   "szLabel": "Callback243Header",
   "szText": "在蕾蕊儿解除大门封印时保护她",
   "hLabel": 2331484751
  },
  {
   "__type__": "StringTableEntry",
   "__typeHash__": 3844612145,
   "szLabel": "Callback384Header",
   "szText": "在蕾蕊儿解除大门封印时保护她",
   "hLabel": 4252345237
  },
  {
   "__type__": "StringTableEntry",
   "__typeHash__": 3844612145,
   "szLabel": "Phase283Description",
   "szText": "我和蕾蕊儿深入上古之城卡萨玛，穿过安眠地的黑暗通道，追寻莉莉丝和维纳德的踪迹。",
   "hLabel": 4198464786
  },
  {
   "__type__": "StringTableEntry",
   "__typeHash__": 3844612145,
   "szLabel": "Phase283OutsideSubzoneHeader",
   "szText": "进入安眠地",
   "hLabel": 3984357018
  },
  {
   "__type__": "StringTableEntry",
   "__typeHash__": 3844612145,
   "szLabel": "Callback285Header",
   "szText": "进入安眠地",
   "hLabel": 3589500757
  },
  {
   "__type__": "StringTableEntry",
   "__typeHash__": 3844612145,
   "szLabel": "Phase326Description",
   "szText": "我和蕾蕊儿深入上古之城卡萨玛，穿过安眠地的黑暗通道，追寻莉莉丝和维纳德的踪迹。",
   "hLabel": 3961492944
  },
  {
   "__type__": "StringTableEntry",
   "__typeHash__": 3844612145,
   "szLabel": "Phase326OutsideSubzoneHeader",
   "szText": "和蕾蕊儿一起追寻莉莉丝和维纳德的踪迹",
   "hLabel": 4174333208
  },
  {
   "__type__": "StringTableEntry",
   "__typeHash__": 3844612145,
   "szLabel": "Callback382Header",
   "szText": "和蕾蕊儿一起追寻莉莉丝和维纳德的踪迹",
   "hLabel": 1669409299
  },
  {
   "__type__": "StringTableEntry",
   "__typeHash__": 3844612145,
   "szLabel": "Phase341Description",
   "szText": "我和蕾蕊儿深入上古之城卡萨玛，穿过安眠地的黑暗通道，追寻莉莉丝和维纳德的踪迹。",
   "hLabel": 2518472173
  },
  {
   "__type__": "StringTableEntry",
   "__typeHash__": 3844612145,
   "szLabel": "Phase341OutsideSubzoneHeader",
   "szText": "和蕾蕊儿一起追寻莉莉丝和维纳德的踪迹",
   "hLabel": 1223095765
  },
  {
   "__type__": "StringTableEntry",
   "__typeHash__": 3844612145,
   "szLabel": "Callback345Header",
   "szText": "消灭{MONSTER}",
   "hLabel": 2573765842
  },
  {
   "__type__": "StringTableEntry",
   "__typeHash__": 3844612145,
   "szLabel": "Phase346Description",
   "szText": "我和蕾蕊儿深入上古之城卡萨玛，穿过安眠地的黑暗通道，追寻莉莉丝和维纳德的踪迹。",
   "hLabel": 2329782482
  },
  {
   "__type__": "StringTableEntry",
   "__typeHash__": 3844612145,
   "szLabel": "Phase346OutsideSubzoneHeader",
   "szText": "和蕾蕊儿一起追寻莉莉丝和维纳德的踪迹",
   "hLabel": 3727153754
  },
  {
   "__type__": "StringTableEntry",
   "__typeHash__": 3844612145,
   "szLabel": "Callback349Header",
   "szText": "检查莉莉丝的血色花瓣",
   "hLabel": 3444670422
  },
  {
   "__type__": "StringTableEntry",
   "__typeHash__": 3844612145,
   "szLabel": "Phase350Description",
   "szText": "我和蕾蕊儿深入上古之城卡萨玛，穿过安眠地的黑暗通道，追寻莉莉丝和维纳德的踪迹。",
   "hLabel": 3028845069
  },
  {
   "__type__": "StringTableEntry",
   "__typeHash__": 3844612145,
   "szLabel": "Phase350OutsideSubzoneHeader",
   "szText": "和蕾蕊儿一起追寻莉莉丝和维纳德的踪迹",
   "hLabel": 1787184629
  },
  {
   "__type__": "StringTableEntry",
   "__typeHash__": 3844612145,
   "szLabel": "Callback381Header",
   "szText": "和蕾蕊儿一起追寻莉莉丝和维纳德的踪迹",
   "hLabel": 377941330
  },
  {
   "__type__": "StringTableEntry",
   "__typeHash__": 3844612145,
   "szLabel": "Phase358Description",
   "szText": "我和蕾蕊儿深入上古之城卡萨玛，穿过安眠地的黑暗通道，追寻莉莉丝和维纳德的踪迹。",
   "hLabel": 1008954645
  },
  {
   "__type__": "StringTableEntry",
   "__typeHash__": 3844612145,
   "szLabel": "Phase358OutsideSubzoneHeader",
   "szText": "和蕾蕊儿一起追寻莉莉丝和维纳德的踪迹",
   "hLabel": 4075690493
  },
  {
   "__type__": "StringTableEntry",
   "__typeHash__": 3844612145,
   "szLabel": "Callback360Header",
   "szText": "检查莉莉丝的血色花瓣",
   "hLabel": 4043900623
  },
  {
   "__type__": "StringTableEntry",
   "__typeHash__": 3844612145,
   "szLabel": "Phase362Description",
   "szText": "我和蕾蕊儿深入上古之城卡萨玛，穿过安眠地的黑暗通道，追寻莉莉丝和维纳德的踪迹。",
   "hLabel": 1708017232
  },
  {
   "__type__": "StringTableEntry",
   "__typeHash__": 3844612145,
   "szLabel": "Phase362OutsideSubzoneHeader",
   "szText": "和蕾蕊儿一起追寻莉莉丝和维纳德的踪迹",
   "hLabel": 2135721368
  },
  {
   "__type__": "StringTableEntry",
   "__typeHash__": 3844612145,
   "szLabel": "Callback364Header",
   "szText": "打开远古之门",
   "hLabel": 619837907
  },
  {
   "__type__": "StringTableEntry",
   "__typeHash__": 3844612145,
   "szLabel": "Phase366Description",
   "szText": "我和蕾蕊儿深入上古之城卡萨玛，穿过安眠地的黑暗通道，追寻莉莉丝和维纳德的踪迹。",
   "hLabel": 698072020
  },
  {
   "__type__": "StringTableEntry",
   "__typeHash__": 3844612145,
   "szLabel": "Phase366OutsideSubzoneHeader",
   "szText": "和蕾蕊儿一起追寻莉莉丝和维纳德的踪迹",
   "hLabel": 3279974300
  },
  {
   "__type__": "StringTableEntry",
   "__typeHash__": 3844612145,
   "szLabel": "Callback375Header",
   "szText": "打开远古之门",
   "hLabel": 1580075893
  },
  {
   "__type__": "StringTableEntry",
   "__typeHash__": 3844612145,
   "szLabel": "Phase370Description",
   "szText": "我和蕾蕊儿深入上古之城卡萨玛，穿过安眠地的黑暗通道，追寻莉莉丝和维纳德的踪迹。",
   "hLabel": 1397134607
  },
  {
   "__type__": "StringTableEntry",
   "__typeHash__": 3844612145,
   "szLabel": "Phase370OutsideSubzoneHeader",
   "szText": "和蕾蕊儿一起追寻莉莉丝和维纳德的踪迹",
   "hLabel": 1340005175
  },
  {
   "__type__": "StringTableEntry",
   "__typeHash__": 3844612145,
   "szLabel": "Callback377Header",
   "szText": "打开远古之门",
   "hLabel": 4163011831
  },
  {
   "__type__": "StringTableEntry",
   "__typeHash__": 3844612145,
   "szLabel": "Phase403Description",
   "szText": "我和蕾蕊儿深入上古之城卡萨玛，穿过安眠地的黑暗通道，追寻莉莉丝和维纳德的踪迹。",
   "hLabel": 4123501644
  },
  {
   "__type__": "StringTableEntry",
   "__typeHash__": 3844612145,
   "szLabel": "Phase403OutsideSubzoneHeader",
   "szText": "和蕾蕊儿一起追寻莉莉丝和维纳德的踪迹",
   "hLabel": 3901054740
  },
  {
   "__type__": "StringTableEntry",
   "__typeHash__": 3844612145,
   "szLabel": "Callback405Header",
   "szText": "和蕾蕊儿一起追寻莉莉丝和维纳德的踪迹",
   "hLabel": 1558030927
  }
 ],
 "ptMapStringTable": "0"
}
