{
 "__fileName__": "plPL_Text/meta/StringList/Conv_QST_Scos_SignTimes_Nairne02.stl",
 "__snoID__": 730372,
 "__type__": "StringListDefinition",
 "__typeHash__": 3672216444,
 "arStrings": [
  {
   "__type__": "StringTableEntry",
   "__typeHash__": 3844612145,
   "szLabel": "MenuLabel",
   "szText": "Wspomnienia o Gęsi",
   "hLabel": 4215274549
  },
  {
   "__type__": "StringTableEntry",
   "__typeHash__": 3844612145,
   "szLabel": "Line3.B20CF",
   "szText": "Nie robię tego dla ciebie. Mówiłam co innego, ale… wiesz, o co chodzi.",
   "hLabel": 4145321526
  },
  {
   "__type__": "StringTableEntry",
   "__typeHash__": 3844612145,
   "szLabel": "Line13.B20CF",
   "szText": "Uch... Na kogo będzie się teraz złościł Torben? Ja nie potrafię go tak wkurzyć. (chłodny śmiech)",
   "hLabel": 203389511
  },
  {
   "__type__": "StringTableEntry",
   "__typeHash__": 3844612145,
   "szLabel": "Line15.B20CF",
   "szText": "(ciężkie westchnięcie) Proszę… Odnieś Gęś do jej gniazda.",
   "hLabel": 2786325449
  },
  {
   "__type__": "StringTableEntry",
   "__typeHash__": 3844612145,
   "szLabel": "Line17.B20CF",
   "szText": "Zostanę jeszcze chwilę i... dokończę ostatnią kolejkę z Tawiszem. Tylko jedną…",
   "hLabel": 1074294091
  },
  {
   "__type__": "StringTableEntry",
   "__typeHash__": 3844612145,
   "szLabel": "Line13.B20CF.F",
   "szText": "Uch... Na kogo będzie się teraz złościł Torben? Ja nie potrafię go tak wkurzyć. (chłodny śmiech)",
   "hLabel": 2447847003
  },
  {
   "__type__": "StringTableEntry",
   "__typeHash__": 3844612145,
   "szLabel": "Line15.B20CF.F",
   "szText": "(ciężkie westchnięcie) Proszę… Odnieś Gęś do jej gniazda.",
   "hLabel": 2061504605
  },
  {
   "__type__": "StringTableEntry",
   "__typeHash__": 3844612145,
   "szLabel": "Line17.B20CF.F",
   "szText": "Zostanę jeszcze chwilę i... dokończę ostatnią kolejkę z Tawiszem. Tylko jedną…",
   "hLabel": 1675162207
  },
  {
   "__type__": "StringTableEntry",
   "__typeHash__": 3844612145,
   "szLabel": "Line3.B20CF.F",
   "szText": "Nie robię tego dla ciebie. Mówiłam co innego, ale… wiesz, o co chodzi.",
   "hLabel": 244515338
  }
 ],
 "ptMapStringTable": "0"
}
